<?xml version="1.0" encoding="UTF-8"?>
<objects serializationModel="Studio.02.02.00">
	<object class="AudioFile" id="{0f55d1bf-ef04-4d2a-9661-d341a49f76d3}">
		<property name="assetPath">
			<value>Player/Attack/Player_Attack_AxeSwing04.wav</value>
		</property>
		<property name="frequencyInKHz">
			<value>44.0999985</value>
		</property>
		<property name="channelCount">
			<value>2</value>
		</property>
		<property name="length">
			<value>1.1704308390022675</value>
		</property>
		<relationship name="masterAssetFolder">
			<destination>{30f14458-d000-4740-9a20-f17c5723a325}</destination>
		</relationship>
	</object>
</objects>
