<?xml version="1.0" encoding="UTF-8"?>
<objects serializationModel="Studio.02.02.00">
	<object class="AudioFile" id="{86ac5b0c-7450-486a-b2f9-7447af60e4a9}">
		<property name="assetPath">
			<value>Cutscene/Cutscene_Fox_Breathing.wav</value>
		</property>
		<property name="frequencyInKHz">
			<value>44.0999985</value>
		</property>
		<property name="channelCount">
			<value>2</value>
		</property>
		<property name="length">
			<value>3.5</value>
		</property>
		<relationship name="masterAssetFolder">
			<destination>{30f14458-d000-4740-9a20-f17c5723a325}</destination>
		</relationship>
	</object>
</objects>
